blackjack_cli/__init__.py
blackjack_cli/blackjack.py
blackjack_cli/config.py
blackjack_cli/console.py
blackjack_cli/models/__init__.py
blackjack_cli/models/stats_model.py
blackjack_cli/stats.py
deck/__init__.py
deck/card.py
deck/cardhand.py
deck/deck.py
blackjack_cli-1.1.0.dist-info/METADATA
blackjack_cli-1.1.0.dist-info/WHEEL
blackjack_cli-1.1.0.dist-info/entry_points.txt
blackjack_cli-1.1.0.dist-info/RECORD
